codebooks/__init__.py
codebooks/__main__.py
codebooks/html.py
codebooks/log.py
codebooks/variable.py
codebooks/css/__init__.py
codebooks/css/bootstrap.min.css
codebooks-0.0.6.dist-info/LICENSE
codebooks-0.0.6.dist-info/METADATA
codebooks-0.0.6.dist-info/WHEEL
codebooks-0.0.6.dist-info/entry_points.txt
codebooks-0.0.6.dist-info/top_level.txt
codebooks-0.0.6.dist-info/RECORD
