Metadata-Version: 2.1
Name: codebooks
Version: 0.0.6
Summary: Automatic generation of codebooks from dataframes.
Home-page: https://github.com/mhowison/codebooks
Author: Mark Howison
Author-email: mark@howison.org
License: BSD
Classifier: Development Status :: 3 - Alpha
Classifier: License :: OSI Approved :: BSD License
Classifier: Intended Audience :: Science/Research
Classifier: Operating System :: OS Independent
Classifier: Natural Language :: English
Classifier: Programming Language :: Python :: 3
Classifier: Topic :: Scientific/Engineering
Requires-Python: >=3.8
License-File: LICENSE
Requires-Dist: htmlmin
Requires-Dist: pandas
Requires-Dist: tqdm
